tensorflow_recommenders/__init__.py
tensorflow_recommenders/public.py
tensorflow_recommenders/types.py
tensorflow_recommenders/examples/__init__.py
tensorflow_recommenders/examples/movielens.py
tensorflow_recommenders/examples/nbtool.py
tensorflow_recommenders/experimental/__init__.py
tensorflow_recommenders/experimental/layers/__init__.py
tensorflow_recommenders/experimental/layers/embedding/__init__.py
tensorflow_recommenders/experimental/layers/embedding/partial_tpu_embedding.py
tensorflow_recommenders/experimental/layers/embedding/partial_tpu_embedding_test.py
tensorflow_recommenders/experimental/models/__init__.py
tensorflow_recommenders/experimental/models/ranking.py
tensorflow_recommenders/experimental/models/ranking_test.py
tensorflow_recommenders/experimental/optimizers/__init__.py
tensorflow_recommenders/experimental/optimizers/clippy_adagrad.py
tensorflow_recommenders/experimental/optimizers/clippy_adagrad_test.py
tensorflow_recommenders/experimental/optimizers/composite_optimizer.py
tensorflow_recommenders/experimental/optimizers/composite_optimizer_test.py
tensorflow_recommenders/layers/__init__.py
tensorflow_recommenders/layers/blocks.py
tensorflow_recommenders/layers/factorized_top_k.py
tensorflow_recommenders/layers/factorized_top_k_test.py
tensorflow_recommenders/layers/loss.py
tensorflow_recommenders/layers/loss_test.py
tensorflow_recommenders/layers/embedding/__init__.py
tensorflow_recommenders/layers/embedding/tpu_embedding_layer.py
tensorflow_recommenders/layers/embedding/tpu_embedding_layer_test.py
tensorflow_recommenders/layers/feature_interaction/__init__.py
tensorflow_recommenders/layers/feature_interaction/dcn.py
tensorflow_recommenders/layers/feature_interaction/dcn_test.py
tensorflow_recommenders/layers/feature_interaction/dot_interaction.py
tensorflow_recommenders/layers/feature_interaction/dot_interaction_test.py
tensorflow_recommenders/layers/feature_interaction/multi_layer_dcn.py
tensorflow_recommenders-0.7.6.dist-info/LICENSE
tensorflow_recommenders-0.7.6.dist-info/METADATA
tensorflow_recommenders-0.7.6.dist-info/WHEEL
tensorflow_recommenders-0.7.6.dist-info/top_level.txt
tensorflow_recommenders-0.7.6.dist-info/RECORD
