Metadata-Version: 2.1
Name: tensorflow-recommenders
Version: 0.7.6
Summary: Tensorflow Recommenders, a TensorFlow library for recommender systems.
Home-page: https://github.com/tensorflow/recommenders
Author: Google Inc.
Author-email: packages@tensorflow.org
License: Apache 2.0
Keywords: tensorflow recommenders recommendations
Platform: UNKNOWN
Classifier: Development Status :: 3 - Alpha
Classifier: Intended Audience :: Developers
Classifier: Intended Audience :: Education
Classifier: Intended Audience :: Science/Research
Classifier: License :: OSI Approved :: Apache Software License
Classifier: Programming Language :: Python :: 3
Classifier: Programming Language :: Python :: 3.8
Classifier: Programming Language :: Python :: 3.9
Classifier: Programming Language :: Python :: 3.10
Classifier: Topic :: Scientific/Engineering
Classifier: Topic :: Scientific/Engineering :: Mathematics
Classifier: Topic :: Scientific/Engineering :: Artificial Intelligence
Classifier: Topic :: Software Development
Classifier: Topic :: Software Development :: Libraries
Classifier: Topic :: Software Development :: Libraries :: Python Modules
Requires-Dist: absl-py (>=0.1.6)
Requires-Dist: tf-keras
Requires-Dist: tensorflow (>=2.9.0) ; sys_platform != "darwin"
Requires-Dist: tensorflow-macos (>=2.9.0) ; sys_platform == "darwin"
Provides-Extra: docs
Requires-Dist: annoy ; extra == 'docs'
Requires-Dist: fire ; extra == 'docs'
Requires-Dist: scann (==1.2.*) ; extra == 'docs'
Requires-Dist: tensorflow-ranking ; extra == 'docs'
